pontiPy.py
pontiPy-3.0.dist-info/METADATA
pontiPy-3.0.dist-info/WHEEL
pontiPy-3.0.dist-info/top_level.txt
pontiPy-3.0.dist-info/RECORD
