Metadata-Version: 2.1
Name: pontiPy
Version: 3.0
Summary: Automation of Pontius Matrix
Home-page: https://github.com/verma-priyanka
Author: Priyanka Verma
Author-email: prverma@clarku.edu
License: MIT
Platform: UNKNOWN
Requires-Dist: pandas
